{"data":{"_disclaimer":"This data is the exclusive property of Electricity Maps and/or related parties. If you're in doubt about your rights to use this data, please contact","createdAt":"2024-12-18T06:23:51.136191Z","datetime":"2024-12-18T03:00:00Z","datetimes":{"2024-12-18T03:00:00Z":{"e":{"AD->ES":{"ci":181,"f":-29},"AL->ME":{"ci":405,"f":-293},"AL->XK":{"ci":458,"f":72},"AR->BR":{"ci":369,"f":0},"AR->BR-S":{"ci":369,"f":0},"AR->PY":{"ci":461,"f":-10},"AT->CH":{"ci":78,"f":-23},"AT->CZ":{"ci":494,"f":-1785.59},"AT->DE":{"ci":216,"f":-2233},"AT->HU":{"ci":279,"f":930.25},"AT->IT":{"ci":279,"f":333},"AT->IT-NO":{"ci":279,"f":333},"AT->SI":{"ci":279,"f":1590},"AU-NSW->AU-QLD":{"ci":271,"f":577.48},"AU-NSW->AU-VIC":{"ci":271,"f":684.33},"AU-SA->AU-VIC":{"ci":57,"f":72.84},"AU-TAS->AU-VIC":{"ci":264,"f":-430.72},"AX->FI":{"ci":155,"f":-2.67},"AX->SE":{"ci":18,"f":-38.15},"AX->SE-SE3":{"ci":24,"f":-38.15},"AZ->GE":{"ci":533,"f":133},"AZ->RU-1":{"ci":533,"f":11.35},"BA->HR":{"ci":360,"f":-820},"BA->RS":{"ci":575,"f":137},"BE->DE":{"ci":65,"f":998.5},"BE->FR":{"ci":26,"f":-568.5},"BE->GB":{"ci":83,"f":-995},"BE->LU":{"ci":65,"f":239},"BE->NL":{"ci":65,"f":1046},"BG->GR":{"ci":441,"f":584},"BG->MK":{"ci":441,"f":265},"BG->RO":{"ci":378,"f":-899},"BG->RS":{"ci":441,"f":30},"BG->TR":{"ci":441,"f":10},"BR-CS->BR-N":{"ci":164,"f":-2865.29},"BR-CS->BR-NE":{"ci":31,"f":-2844.1},"BR-CS->BR-S":{"ci":79,"f":-477.67},"BR-N->BR-NE":{"ci":164,"f":609.07},"BY->LT":{"ci":388,"f":-213.25},"BY->RU-1":{"ci":373,"f":-67.97},"CA-AB->CA-BC":{"ci":56,"f":-147.13},"CA-AB->US":{"ci":393,"f":-142.67},"CA-AB->US-NW-NWMT":{"ci":594,"f":-142.67},"CA-BC->US":{"ci":56,"f":22.67},"CA-BC->US-NW-BPAT":{"ci":56,"f":22.67},"CA-MB->CA-ON":{"ci":79,"f":-22.19},"CA-NB->CA-NS":{"ci":191,"f":45},"CA-NB->CA-QC":{"ci":41,"f":-234},"CA-NB->US":{"ci":191,"f":157},"CA-NB->US-NE-ISNE":{"ci":191,"f":157},"CA-NL-NF->CA-NS":{"ci":461,"f":430.13},"CA-ON->CA-QC":{"ci":79,"f":1324.63},"CA-ON->US":{"ci":79,"f":1319.37},"CA-ON->US-MIDW-MISO":{"ci":79,"f":377.15},"CA-ON->US-NY-NYIS":{"ci":79,"f":942.22},"CA-QC->US":{"ci":393,"f":-523.16},"CA-QC->US-NE-ISNE":{"ci":41,"f":454.68},"CA-QC->US-NY-NYIS":{"ci":305,"f":-977.83},"CH->DE":{"ci":216,"f":-2629.5},"CH->FR":{"ci":26,"f":-3415},"CH->IT":{"ci":78,"f":3985},"CH->IT-NO":{"ci":78,"f":3985},"CN->RU-AS":{"ci":461,"f":100.73},"CR->NI":{"ci":25,"f":165.39},"CZ->DE":{"ci":216,"f":-1521.14},"CZ->PL":{"ci":786,"f":-1066.71},"CZ->SK":{"ci":494,"f":2496.98},"DE->DK":{"ci":65,"f":-1037.4},"DE->DK-DK1":{"ci":44,"f":-248.62},"DE->DK-DK2":{"ci":111,"f":-788.77},"DE->FR":{"ci":26,"f":-4371},"DE->NL":{"ci":152,"f":-3041.75},"DE->NO":{"ci":30,"f":-863.25},"DE->NO-NO2":{"ci":28,"f":-863.25},"DE->SE":{"ci":18,"f":-602},"DE->SE-SE4":{"ci":44,"f":-602},"DK->GB":{"ci":83,"f":-701},"DK->NL":{"ci":65,"f":294.04},"DK->NO":{"ci":65,"f":516.58},"DK->SE":{"ci":18,"f":-209.16},"DK-BHM->SE-SE4":{"ci":44,"f":-8.16},"DK-DK1->DK-DK2":{"ci":111,"f":-36.44},"DK-DK1->GB":{"ci":83,"f":-701},"DK-DK1->NL":{"ci":44,"f":294.04},"DK-DK1->NO-NO2":{"ci":44,"f":516.58},"DK-DK1->SE-SE3":{"ci":44,"f":616},"DK-DK2->SE-SE4":{"ci":44,"f":-817},"EE->FI":{"ci":500,"f":118},"EE->LV":{"ci":399,"f":-428},"EE->RU-1":{"ci":373,"f":-179},"ES->ES-IB-MA":{"ci":181,"f":41.95},"ES->FR":{"ci":26,"f":-2739.75},"ES->MA":{"ci":637,"f":-388.39},"ES->PT":{"ci":181,"f":2601},"ES-IB-FO->ES-IB-IZ":{"ci":489,"f":-3.47},"ES-IB-IZ->ES-IB-MA":{"ci":488,"f":-73.31},"ES-IB-MA->ES-IB-ME":{"ci":488,"f":11.17},"FI->NO":{"ci":30,"f":-11},"FI->NO-NO4":{"ci":47,"f":-11},"FI->SE":{"ci":18,"f":-2124},"FI->SE-SE1":{"ci":15,"f":-931},"FI->SE-SE3":{"ci":24,"f":-1193},"FR->GB":{"ci":83,"f":-2524},"FR->IT":{"ci":26,"f":3094},"FR->IT-NO":{"ci":26,"f":3094},"FR-COR->IT":{"ci":330,"f":-116},"FR-COR->IT-CNO":{"ci":668,"f":110},"FR-COR->IT-SAR":{"ci":702,"f":-226},"GB->GB-NIR":{"ci":266,"f":-170},"GB->GB-ORK":{"ci":14,"f":-15.69},"GB->IE":{"ci":201,"f":-4},"GB->IM":{"ci":83,"f":9},"GB->NL":{"ci":152,"f":-2},"GB->NO":{"ci":83,"f":376.5},"GB->NO-NO2":{"ci":83,"f":376.5},"GE->RU-1":{"ci":373,"f":-305},"GR->IT":{"ci":541,"f":158},"GR->IT-SO":{"ci":541,"f":158},"GT->HN":{"ci":171,"f":31.7},"HN->NI":{"ci":274,"f":27},"HN->SV":{"ci":309,"f":-17.4},"HR->HU":{"ci":315,"f":-1335.75},"HR->RS":{"ci":360,"f":471},"HR->SI":{"ci":309,"f":-603.75},"HU->RO":{"ci":315,"f":888.25},"HU->RS":{"ci":315,"f":508},"HU->SI":{"ci":315,"f":266.75},"HU->SK":{"ci":355,"f":-3097},"HU->UA":{"ci":228,"f":-150},"IT->ME":{"ci":405,"f":-394},"IT->MT":{"ci":330,"f":53},"IT->SI":{"ci":309,"f":-846},"IT-CNO->IT-CSO":{"ci":283,"f":1132},"IT-CNO->IT-NO":{"ci":282,"f":-1755},"IT-CSO->IT-SAR":{"ci":440,"f":140},"IT-CSO->IT-SO":{"ci":334,"f":-703},"IT-CSO->ME":{"ci":405,"f":-394},"IT-NO->SI":{"ci":309,"f":-846},"IT-SIC->IT-SO":{"ci":334,"f":-729},"IT-SIC->MT":{"ci":337,"f":53},"JP-CB->JP-HR":{"ci":457,"f":-298.75},"JP-CB->JP-KN":{"ci":361,"f":-2124.67},"JP-CB->JP-TK":{"ci":383,"f":136.25},"JP-CG->JP-KN":{"ci":412,"f":1471.17},"JP-CG->JP-KY":{"ci":226,"f":-1205},"JP-CG->JP-SK":{"ci":412,"f":1067},"JP-HKD->JP-TH":{"ci":422,"f":-149.67},"JP-HR->JP-KN":{"ci":361,"f":-276.33},"JP-KN->JP-SK":{"ci":311,"f":-138.92},"JP-TH->JP-TK":{"ci":422,"f":4955},"KZ->RU-1":{"ci":682,"f":1886.1},"KZ->RU-2":{"ci":481,"f":-1170.28},"LT->LV":{"ci":388,"f":408},"LT->PL":{"ci":786,"f":-508},"LT->RU-KGD":{"ci":388,"f":12.5},"LV->RU-1":{"ci":373,"f":-7},"MD->RO":{"ci":463,"f":22},"MD->UA":{"ci":463,"f":138},"ME->RS":{"ci":464,"f":-207},"ME->XK":{"ci":405,"f":224},"MK->RS":{"ci":483,"f":72},"MK->XK":{"ci":598,"f":-258},"MN->RU-2":{"ci":713,"f":325.06},"MX->US":{"ci":393,"f":-110.67},"MX-BC->US-CAL-CISO":{"ci":316,"f":-81.37},"MX-NE->US-TEX-ERCO":{"ci":340,"f":-29.3},"MY->SG":{"ci":541,"f":63.04},"MY->TH":{"ci":409,"f":-30},"MY-WM->SG":{"ci":638,"f":63.04},"MY-WM->TH":{"ci":409,"f":-30},"NL->NO":{"ci":30,"f":-238.5},"NL->NO-NO2":{"ci":28,"f":-238.5},"NO->SE":{"ci":30,"f":1141},"NO-NO1->NO-NO2":{"ci":28,"f":-897.25},"NO-NO1->NO-NO3":{"ci":26,"f":-385.5},"NO-NO1->NO-NO5":{"ci":26,"f":-1510},"NO-NO1->SE-SE3":{"ci":26,"f":186},"NO-NO2->NO-NO5":{"ci":26,"f":-173.75},"NO-NO3->NO-NO4":{"ci":47,"f":-425.25},"NO-NO3->NO-NO5":{"ci":26,"f":564.75},"NO-NO3->SE-SE2":{"ci":26,"f":561},"NO-NO4->SE-SE1":{"ci":47,"f":205},"NO-NO4->SE-SE2":{"ci":47,"f":189},"PL->SE":{"ci":18,"f":-597},"PL->SE-SE4":{"ci":44,"f":-597},"PL->SK":{"ci":786,"f":1034},"PL->UA":{"ci":786,"f":240.25},"RO->RS":{"ci":378,"f":156},"RO->UA":{"ci":228,"f":-635},"RS->XK":{"ci":464,"f":348},"RU-1->RU-2":{"ci":373,"f":559.5},"RU-1->UA-CR":{"ci":373,"f":337.54},"SK->UA":{"ci":355,"f":762},"US-CENT-SWPP->US-MIDW-AECI":{"ci":322,"f":123.64},"US-CENT-SWPP->US-MIDW-MISO":{"ci":322,"f":788.37},"US-CENT-SWPP->US-NW-PSCO":{"ci":322,"f":165.34},"US-CENT-SWPP->US-NW-WACM":{"ci":322,"f":132.31},"US-CENT-SWPP->US-NW-WAUW":{"ci":24,"f":-82.59},"US-CENT-SWPP->US-SW-EPE":{"ci":685,"f":-0.11},"US-CENT-SWPP->US-TEX-ERCO":{"ci":322,"f":22.67},"US-FLA-FPL->US-FLA-HST":{"ci":301,"f":74.92},"US-MIDA-PJM->US-MIDW-MISO":{"ci":424,"f":3382.37},"US-MIDA-PJM->US-NY-NYIS":{"ci":424,"f":2552.36},"US-MIDA-PJM->US-TEN-TVA":{"ci":346,"f":-1635.69},"US-NE-ISNE->US-NY-NYIS":{"ci":305,"f":-345.65}},"z":{"AE":{"c":{"ci":382,"fr":0.7728,"rr":0},"e":true,"p":{"ci":382,"fr":0.7728,"rr":0}},"AR":{"c":{"ci":369,"fr":0.5131,"rr":0.421},"p":{"ci":369,"fr":0.513,"rr":0.4211}},"AT":{"c":{"ci":279,"fr":0.3733,"rr":0.5324},"p":{"ci":230,"fr":0.41,"rr":0.59}},"AU":{"c":{"ci":296,"fr":0.3471,"rr":0.6529},"p":{"ci":297,"fr":0.3473,"rr":0.6527}},"AU-NSW":{"c":{"ci":271,"fr":0.2962,"rr":0.7038},"p":{"ci":271,"fr":0.2963,"rr":0.7037}},"AU-NT":{"c":{"ci":504,"fr":0.9954,"rr":0.0046},"e":true,"p":{"ci":504,"fr":0.9954,"rr":0.0046}},"AU-QLD":{"c":{"ci":431,"fr":0.5362,"rr":0.4638},"p":{"ci":440,"fr":0.55,"rr":0.45}},"AU-SA":{"c":{"ci":57,"fr":0.0372,"rr":0.9628},"p":{"ci":57,"fr":0.0363,"rr":0.9637}},"AU-TAS":{"c":{"ci":116,"fr":0.1057,"rr":0.8943},"p":{"ci":29,"fr":0,"rr":1}},"AU-TAS-FI":{"c":{"ci":34,"fr":0,"rr":1},"p":{"ci":34,"fr":0,"rr":1}},"AU-TAS-KI":{"c":{"ci":484,"fr":0.7305,"rr":0.2695},"p":{"ci":486,"fr":0.7334,"rr":0.2666}},"AU-VIC":{"c":{"ci":264,"fr":0.285,"rr":0.715},"p":{"ci":266,"fr":0.287,"rr":0.713}},"AU-WA":{"c":{"ci":209,"fr":0.2586,"rr":0.7414},"e":true,"p":{"ci":209,"fr":0.2586,"rr":0.7414}},"AU-WA-RI":{"c":{"ci":332,"fr":0.4894,"rr":0.5106},"p":{"ci":332,"fr":0.4894,"rr":0.5106}},"AW":{"c":{"ci":530,"fr":0.8117,"rr":0.1883},"p":{"ci":530,"fr":0.8117,"rr":0.1883}},"AX":{"c":{"ci":32,"fr":0.014,"rr":0.3787},"p":{"ci":13,"fr":0,"rr":1}},"BA":{"c":{"ci":575,"fr":0.6976,"rr":0.2027},"p":{"ci":699,"fr":0.8506,"rr":0.1494}},"BD":{"c":{"ci":600,"fr":0.9591,"rr":0.0409},"e":true,"p":{"ci":600,"fr":0.9591,"rr":0.0409}},"BE":{"c":{"ci":65,"fr":0.0885,"rr":0.4793},"p":{"ci":66,"fr":0.0884,"rr":0.4624}},"BG":{"c":{"ci":441,"fr":0.4423,"rr":0.1102},"p":{"ci":454,"fr":0.4444,"rr":0.0774}},"BH":{"c":{"ci":null,"fr":null,"rr":null},"o":true,"p":{"ci":null,"fr":null,"rr":null}},"BO":{"c":{"ci":323,"fr":0.6491,"rr":0.3509},"p":{"ci":323,"fr":0.6491,"rr":0.3509}},"BR":{"c":{"ci":82,"fr":0.0888,"rr":0.903},"p":{"ci":82,"fr":0.0888,"rr":0.903}},"BR-CS":{"c":{"ci":84,"fr":0.0905,"rr":0.8948},"p":{"ci":82,"fr":0.0866,"rr":0.8962}},"BR-N":{"c":{"ci":164,"fr":0.2081,"rr":0.7919},"p":{"ci":164,"fr":0.2078,"rr":0.7922}},"BR-NE":{"c":{"ci":31,"fr":0.0254,"rr":0.9746},"p":{"ci":26,"fr":0.0188,"rr":0.9812}},"BR-S":{"c":{"ci":79,"fr":0.0822,"rr":0.9178},"p":{"ci":79,"fr":0.0822,"rr":0.9178}},"CA-AB":{"c":{"ci":451,"fr":0.8993,"rr":0.1007},"p":{"ci":455,"fr":0.9141,"rr":0.0859}},"CA-BC":{"c":{"ci":56,"fr":0.06,"rr":0.94},"e":true,"p":{"ci":56,"fr":0.06,"rr":0.94}},"CA-NB":{"c":{"ci":191,"fr":0.2631,"rr":0.4029},"p":{"ci":212,"fr":0.2962,"rr":0.3284}},"CA-ON":{"c":{"ci":79,"fr":0.1413,"rr":0.2929},"p":{"ci":79,"fr":0.1413,"rr":0.2929}},"CA-QC":{"c":{"ci":41,"fr":0.0273,"rr":0.9343},"e":true,"p":{"ci":28,"fr":0.0001,"rr":0.9999}},"CA-SK":{"c":{"ci":null,"fr":null,"rr":null},"o":true,"p":{"ci":null,"fr":null,"rr":null}},"CA-YT":{"c":{"ci":279,"fr":0.3773,"rr":0.6227},"p":{"ci":279,"fr":0.3773,"rr":0.6227}},"CH":{"c":{"ci":78,"fr":0.0672,"rr":0.4597},"p":{"ci":45,"fr":0.0139,"rr":0.4494}},"CL-SEN":{"c":{"ci":252,"fr":0.3663,"rr":0.6337},"e":true,"p":{"ci":252,"fr":0.3663,"rr":0.6337}},"CO":{"c":{"ci":160,"fr":0.2209,"rr":0.7791},"e":true,"p":{"ci":160,"fr":0.2209,"rr":0.7791}},"CR":{"c":{"ci":25,"fr":0,"rr":1},"p":{"ci":25,"fr":0,"rr":1}},"CY":{"c":{"ci":858,"fr":0.9644,"rr":0.0356},"p":{"ci":858,"fr":0.9644,"rr":0.0356}},"CZ":{"c":{"ci":494,"fr":0.4555,"rr":0.1559},"e":true,"p":{"ci":507,"fr":0.4568,"rr":0.0467}},"DE":{"c":{"ci":216,"fr":0.2304,"rr":0.7081},"p":{"ci":248,"fr":0.2617,"rr":0.7383}},"DK":{"c":{"ci":65,"fr":0.0525,"rr":0.9344},"p":{"ci":66,"fr":0.0514,"rr":0.9486}},"DK-BHM":{"c":{"ci":35,"fr":0.0008,"rr":0.9992},"p":{"ci":29,"fr":0,"rr":1}},"DK-DK1":{"c":{"ci":44,"fr":0.0397,"rr":0.9412},"p":{"ci":37,"fr":0.0256,"rr":0.9744}},"DK-DK2":{"c":{"ci":111,"fr":0.0817,"rr":0.9183},"p":{"ci":147,"fr":0.1248,"rr":0.8752}},"EE":{"c":{"ci":500,"fr":0.641,"rr":0.3147},"p":{"ci":652,"fr":0.6147,"rr":0.3853}},"ES":{"c":{"ci":181,"fr":0.2814,"rr":0.442},"p":{"ci":193,"fr":0.3033,"rr":0.4659}},"ES-CE":{"c":{"ci":649,"fr":1,"rr":0},"p":{"ci":649,"fr":1,"rr":0}},"ES-CN-FVLZ":{"c":{"ci":749,"fr":0.7912,"rr":0.2088},"p":{"ci":749,"fr":0.7912,"rr":0.2088}},"ES-CN-GC":{"c":{"ci":893,"fr":0.9559,"rr":0.0441},"p":{"ci":893,"fr":0.9559,"rr":0.0441}},"ES-CN-HI":{"c":{"ci":470,"fr":0.4831,"rr":0.5169},"p":{"ci":472,"fr":0.4814,"rr":0.5186}},"ES-CN-IG":{"c":{"ci":867,"fr":0.9046,"rr":0.0954},"p":{"ci":867,"fr":0.9046,"rr":0.0954}},"ES-CN-LP":{"c":{"ci":920,"fr":0.9984,"rr":0.0016},"p":{"ci":920,"fr":0.9984,"rr":0.0016}},"ES-CN-TE":{"c":{"ci":903,"fr":0.9617,"rr":0.0383},"p":{"ci":903,"fr":0.9617,"rr":0.0383}},"ES-IB-FO":{"c":{"ci":489,"fr":0.8516,"rr":0.12},"p":{"ci":null,"fr":null,"rr":null}},"ES-IB-IZ":{"c":{"ci":489,"fr":0.8516,"rr":0.1201},"p":{"ci":700,"fr":1,"rr":0}},"ES-IB-MA":{"c":{"ci":488,"fr":0.8504,"rr":0.121},"p":{"ci":523,"fr":0.9159,"rr":0.0841}},"ES-IB-ME":{"c":{"ci":865,"fr":0.9453,"rr":0.0443},"p":{"ci":1083,"fr":1,"rr":0}},"ES-ML":{"c":{"ci":606,"fr":0.8953,"rr":0.1047},"p":{"ci":606,"fr":0.8953,"rr":0.1047}},"FI":{"c":{"ci":155,"fr":0.1635,"rr":0.4075},"p":{"ci":183,"fr":0.1945,"rr":0.3535}},"FO":{"c":{"ci":581,"fr":0.6475,"rr":0.3525},"p":{"ci":581,"fr":0.6475,"rr":0.3525}},"FO-MI":{"c":{"ci":580,"fr":0.646,"rr":0.354},"p":{"ci":580,"fr":0.646,"rr":0.354}},"FO-SI":{"c":{"ci":592,"fr":0.6636,"rr":0.3364},"p":{"ci":592,"fr":0.6636,"rr":0.3364}},"FR":{"c":{"ci":26,"fr":0.0294,"rr":0.285},"p":{"ci":24,"fr":0.0258,"rr":0.2677}},"FR-COR":{"c":{"ci":668,"fr":0.7936,"rr":0.2036},"p":{"ci":611,"fr":0.6823,"rr":0.3177}},"GB":{"c":{"ci":83,"fr":0.1233,"rr":0.7401},"p":{"ci":82,"fr":0.1216,"rr":0.741}},"GB-NIR":{"c":{"ci":266,"fr":0.4685,"rr":0.5315},"e":true,"p":{"ci":266,"fr":0.4685,"rr":0.5315}},"GB-ORK":{"c":{"ci":14,"fr":0,"rr":1},"p":{"ci":14,"fr":0,"rr":1}},"GE":{"c":{"ci":290,"fr":0.5496,"rr":0.4018},"p":{"ci":240,"fr":0.4645,"rr":0.5355}},"GF":{"c":{"ci":445,"fr":0.669,"rr":0.331},"p":{"ci":445,"fr":0.669,"rr":0.331}},"GP":{"c":{"ci":520,"fr":0.7232,"rr":0.2768},"p":{"ci":520,"fr":0.7232,"rr":0.2768}},"GR":{"c":{"ci":541,"fr":0.8433,"rr":0.087},"e":true,"p":{"ci":559,"fr":0.9173,"rr":0.0827}},"GT":{"c":{"ci":171,"fr":0.1446,"rr":0.8554},"p":{"ci":171,"fr":0.1446,"rr":0.8554}},"HK":{"c":{"ci":null,"fr":null,"rr":null},"o":true,"p":{"ci":null,"fr":null,"rr":null}},"HN":{"c":{"ci":274,"fr":0.3741,"rr":0.6259},"p":{"ci":276,"fr":0.3791,"rr":0.6209}},"HR":{"c":{"ci":360,"fr":0.434,"rr":0.2948},"p":{"ci":459,"fr":0.5537,"rr":0.4463}},"HU":{"c":{"ci":315,"fr":0.3636,"rr":0.1582},"p":{"ci":293,"fr":0.3733,"rr":0.0709}},"ID":{"c":{"ci":null,"fr":null,"rr":null},"o":true,"p":{"ci":null,"fr":null,"rr":null}},"IE":{"c":{"ci":201,"fr":0.2598,"rr":0.7402},"e":true,"p":{"ci":201,"fr":0.2598,"rr":0.7402}},"IL":{"c":{"ci":571,"fr":0.9997,"rr":0.0003},"e":true,"p":{"ci":571,"fr":0.9997,"rr":0.0003}},"IN":{"c":{"ci":647,"fr":0.7841,"rr":0.1801},"e":true,"p":{"ci":647,"fr":0.7841,"rr":0.1801}},"IN-EA":{"c":{"ci":795,"fr":0.9691,"rr":0.0309},"e":true,"p":{"ci":795,"fr":0.9691,"rr":0.0309}},"IN-MH":{"c":{"ci":641,"fr":0.7745,"rr":0.2011},"p":{"ci":641,"fr":0.7745,"rr":0.2011}},"IN-NE":{"c":{"ci":395,"fr":0.6711,"rr":0.3289},"e":true,"p":{"ci":395,"fr":0.6711,"rr":0.3289}},"IN-NO":{"c":{"ci":578,"fr":0.6923,"rr":0.2831},"e":true,"p":{"ci":578,"fr":0.6923,"rr":0.2831}},"IN-PB":{"c":{"ci":726,"fr":0.8784,"rr":0.1216},"p":{"ci":726,"fr":0.8784,"rr":0.1216}},"IN-SO":{"c":{"ci":487,"fr":0.5788,"rr":0.3604},"e":true,"p":{"ci":487,"fr":0.5788,"rr":0.3604}},"IN-WE":{"c":{"ci":762,"fr":0.9301,"rr":0.0262},"e":true,"p":{"ci":762,"fr":0.9301,"rr":0.0262}},"IS":{"c":{"ci":28,"fr":0,"rr":1},"p":{"ci":28,"fr":0,"rr":1}},"IT":{"c":{"ci":330,"fr":0.5095,"rr":0.3254},"p":{"ci":445,"fr":0.7077,"rr":0.2923}},"IT-CNO":{"c":{"ci":283,"fr":0.4559,"rr":0.4025},"p":{"ci":253,"fr":0.4201,"rr":0.5799}},"IT-CSO":{"c":{"ci":440,"fr":0.5898,"rr":0.3753},"p":{"ci":542,"fr":0.6726,"rr":0.3274}},"IT-NO":{"c":{"ci":282,"fr":0.4608,"rr":0.286},"p":{"ci":462,"fr":0.8046,"rr":0.1954}},"IT-SAR":{"c":{"ci":702,"fr":0.8581,"rr":0.1375},"p":{"ci":740,"fr":0.8974,"rr":0.1026}},"IT-SIC":{"c":{"ci":337,"fr":0.5856,"rr":0.4126},"p":{"ci":341,"fr":0.6177,"rr":0.3823}},"IT-SO":{"c":{"ci":334,"fr":0.5538,"rr":0.4427},"p":{"ci":323,"fr":0.5386,"rr":0.4614}},"JP":{"c":{"ci":382,"fr":0.5664,"rr":0.3619},"e":true,"p":{"ci":384,"fr":0.5664,"rr":0.3619}},"JP-CB":{"c":{"ci":383,"fr":0.5629,"rr":0.4153},"e":true,"p":{"ci":384,"fr":0.5637,"rr":0.4363}},"JP-CG":{"c":{"ci":412,"fr":0.6068,"rr":0.3532},"e":true,"p":{"ci":437,"fr":0.6465,"rr":0.3535}},"JP-HKD":{"c":{"ci":406,"fr":0.5913,"rr":0.4087},"e":true,"p":{"ci":406,"fr":0.59,"rr":0.41}},"JP-HR":{"c":{"ci":457,"fr":0.6919,"rr":0.2965},"e":true,"p":{"ci":463,"fr":0.7021,"rr":0.2979}},"JP-KN":{"c":{"ci":361,"fr":0.536,"rr":0.2751},"e":true,"p":{"ci":357,"fr":0.5305,"rr":0.2684}},"JP-KY":{"c":{"ci":226,"fr":0.313,"rr":0.3508},"e":true,"p":{"ci":226,"fr":0.313,"rr":0.3508}},"JP-ON":{"c":{"ci":595,"fr":0.9032,"rr":0.0968},"e":true,"p":{"ci":595,"fr":0.9032,"rr":0.0968}},"JP-SK":{"c":{"ci":311,"fr":0.5646,"rr":0.3833},"p":{"ci":272,"fr":0.5484,"rr":0.3948}},"JP-TH":{"c":{"ci":422,"fr":0.6277,"rr":0.3723},"e":true,"p":{"ci":422,"fr":0.6277,"rr":0.3723}},"JP-TK":{"c":{"ci":413,"fr":0.6121,"rr":0.3877},"e":true,"p":{"ci":412,"fr":0.61,"rr":0.39}},"KR":{"c":{"ci":425,"fr":0.6473,"rr":0.0514},"p":{"ci":425,"fr":0.6473,"rr":0.0514}},"KW":{"c":{"ci":null,"fr":null,"rr":null},"o":true,"p":{"ci":null,"fr":null,"rr":null}},"LK":{"c":{"ci":197,"fr":0.2146,"rr":0.7854},"e":true,"p":{"ci":197,"fr":0.2146,"rr":0.7854}},"LT":{"c":{"ci":388,"fr":0.3833,"rr":0.6167},"p":{"ci":127,"fr":0.1321,"rr":0.8679}},"LU":{"c":{"ci":75,"fr":0.0434,"rr":0.745},"p":{"ci":84,"fr":0,"rr":1}},"LV":{"c":{"ci":399,"fr":0.6405,"rr":0.3579},"p":{"ci":405,"fr":0.793,"rr":0.207}},"MD":{"c":{"ci":463,"fr":0.9252,"rr":0.0748},"p":{"ci":463,"fr":0.9252,"rr":0.0748}},"MK":{"c":{"ci":483,"fr":0.6267,"rr":0.2636},"e":true,"p":{"ci":455,"fr":0.6562,"rr":0.3438}},"MQ":{"c":{"ci":566,"fr":0.8101,"rr":0.1899},"p":{"ci":566,"fr":0.8101,"rr":0.1899}},"MX":{"c":{"ci":null,"fr":null,"rr":null},"o":true,"p":{"ci":null,"fr":null,"rr":null}},"MX-BC":{"c":{"ci":null,"fr":null,"rr":null},"o":true,"p":{"ci":null,"fr":null,"rr":null}},"MX-BCS":{"c":{"ci":null,"fr":null,"rr":null},"o":true,"p":{"ci":null,"fr":null,"rr":null}},"MX-CE":{"c":{"ci":null,"fr":null,"rr":null},"o":true,"p":{"ci":null,"fr":null,"rr":null}},"MX-NE":{"c":{"ci":null,"fr":null,"rr":null},"o":true,"p":{"ci":null,"fr":null,"rr":null}},"MX-NO":{"c":{"ci":null,"fr":null,"rr":null},"o":true,"p":{"ci":null,"fr":null,"rr":null}},"MX-NW":{"c":{"ci":null,"fr":null,"rr":null},"o":true,"p":{"ci":null,"fr":null,"rr":null}},"MX-OC":{"c":{"ci":null,"fr":null,"rr":null},"o":true,"p":{"ci":null,"fr":null,"rr":null}},"MX-OR":{"c":{"ci":null,"fr":null,"rr":null},"o":true,"p":{"ci":null,"fr":null,"rr":null}},"MX-PN":{"c":{"ci":null,"fr":null,"rr":null},"o":true,"p":{"ci":null,"fr":null,"rr":null}},"MY":{"c":{"ci":541,"fr":0.7711,"rr":0.2289},"p":{"ci":542,"fr":0.7713,"rr":0.2287}},"MY-EM":{"c":{"ci":null,"fr":null,"rr":null},"o":true,"p":{"ci":null,"fr":null,"rr":null}},"MY-WM":{"c":{"ci":638,"fr":0.8808,"rr":0.1192},"p":{"ci":639,"fr":0.8809,"rr":0.1191}},"NG":{"c":{"ci":434,"fr":0.8794,"rr":0.1206},"p":{"ci":434,"fr":0.8794,"rr":0.1206}},"NI":{"c":{"ci":161,"fr":0.1685,"rr":0.8315},"p":{"ci":198,"fr":0.2104,"rr":0.7896}},"NL":{"c":{"ci":152,"fr":0.2309,"rr":0.7054},"p":{"ci":163,"fr":0.2503,"rr":0.7131}},"NO":{"c":{"ci":30,"fr":0.0141,"rr":0.983},"p":{"ci":28,"fr":0.0117,"rr":0.9883}},"NO-NO1":{"c":{"ci":26,"fr":0.0043,"rr":0.9939},"p":{"ci":25,"fr":0,"rr":1}},"NO-NO2":{"c":{"ci":28,"fr":0.0124,"rr":0.9784},"p":{"ci":23,"fr":0.0027,"rr":0.9973}},"NO-NO3":{"c":{"ci":26,"fr":0.009,"rr":0.991},"p":{"ci":24,"fr":0.0054,"rr":0.9946}},"NO-NO4":{"c":{"ci":47,"fr":0.0479,"rr":0.9521},"p":{"ci":47,"fr":0.0479,"rr":0.9521}},"NO-NO5":{"c":{"ci":26,"fr":0.004,"rr":0.996},"p":{"ci":26,"fr":0.0031,"rr":0.9969}},"NZ":{"c":{"ci":36,"fr":0.0162,"rr":0.9838},"p":{"ci":36,"fr":0.0162,"rr":0.9838}},"OM":{"c":{"ci":494,"fr":0.9994,"rr":0.0006},"e":true,"p":{"ci":494,"fr":0.9994,"rr":0.0006}},"PA":{"c":{"ci":85,"fr":0.1289,"rr":0.8711},"p":{"ci":85,"fr":0.1289,"rr":0.8711}},"PE":{"c":{"ci":127,"fr":0.222,"rr":0.778},"p":{"ci":127,"fr":0.222,"rr":0.778}},"PF":{"c":{"ci":273,"fr":0.3957,"rr":0.6043},"p":{"ci":273,"fr":0.3957,"rr":0.6043}},"PH":{"c":{"ci":589,"fr":0.7462,"rr":0.2538},"e":true,"p":{"ci":587,"fr":0.7452,"rr":0.2548}},"PH-LU":{"c":{"ci":604,"fr":0.7753,"rr":0.2247},"e":true,"p":{"ci":602,"fr":0.7753,"rr":0.2247}},"PH-MI":{"c":{"ci":575,"fr":0.7017,"rr":0.2983},"e":true,"p":{"ci":575,"fr":0.7017,"rr":0.2983}},"PH-VI":{"c":{"ci":526,"fr":0.6363,"rr":0.3637},"e":true,"p":{"ci":526,"fr":0.6363,"rr":0.3637}},"PL":{"c":{"ci":786,"fr":0.7656,"rr":0.2344},"p":{"ci":813,"fr":0.793,"rr":0.207}},"PT":{"c":{"ci":164,"fr":0.2627,"rr":0.6306},"p":{"ci":153,"fr":0.251,"rr":0.749}},"QA":{"c":{"ci":489,"fr":0.9978,"rr":0.0022},"e":true,"p":{"ci":489,"fr":0.9978,"rr":0.0022}},"RE":{"c":{"ci":196,"fr":0,"rr":1},"p":{"ci":196,"fr":0,"rr":1}},"RO":{"c":{"ci":378,"fr":0.4322,"rr":0.2688},"p":{"ci":406,"fr":0.458,"rr":0.3034}},"RS":{"c":{"ci":null,"fr":null,"rr":null},"o":true,"p":{"ci":null,"fr":null,"rr":null}},"RU":{"c":{"ci":391,"fr":0.6808,"rr":0.1255},"p":{"ci":391,"fr":0.6808,"rr":0.1255}},"RU-1":{"c":{"ci":373,"fr":0.7062,"rr":0.0396},"p":{"ci":367,"fr":0.7029,"rr":0.0387}},"RU-2":{"c":{"ci":481,"fr":0.6059,"rr":0.3896},"p":{"ci":481,"fr":0.6012,"rr":0.3988}},"RU-AS":{"c":{"ci":468,"fr":0.67,"rr":0.3286},"p":{"ci":468,"fr":0.6703,"rr":0.3297}},"SE":{"c":{"ci":18,"fr":0.0029,"rr":0.7144},"p":{"ci":18,"fr":0.0006,"rr":0.6943}},"SE-SE1":{"c":{"ci":15,"fr":0.0033,"rr":0.9967},"p":{"ci":13,"fr":0.0001,"rr":0.9999}},"SE-SE2":{"c":{"ci":14,"fr":0.0019,"rr":0.9981},"p":{"ci":12,"fr":0.0001,"rr":0.9999}},"SE-SE3":{"c":{"ci":24,"fr":0.0037,"rr":0.3678},"p":{"ci":22,"fr":0.0011,"rr":0.3124}},"SE-SE4":{"c":{"ci":44,"fr":0.0023,"rr":0.9977},"p":{"ci":44,"fr":0.0023,"rr":0.9977}},"SG":{"c":{"ci":486,"fr":0.959,"rr":0.041},"p":{"ci":485,"fr":0.9596,"rr":0.0404}},"SI":{"c":{"ci":309,"fr":0.3683,"rr":0.3156},"p":{"ci":346,"fr":0.3628,"rr":0.0704}},"SK":{"c":{"ci":355,"fr":0.353,"rr":0.1454},"p":{"ci":109,"fr":0.1408,"rr":0.1085}},"TH":{"c":{"ci":null,"fr":null,"rr":null},"o":true,"p":{"ci":null,"fr":null,"rr":null}},"TR":{"c":{"ci":554,"fr":0.8066,"rr":0.1933},"e":true,"p":{"ci":554,"fr":0.8067,"rr":0.1933}},"TW":{"c":{"ci":438,"fr":0.7073,"rr":0.2617},"p":{"ci":438,"fr":0.7073,"rr":0.2617}},"US":{"c":{"ci":393,"fr":0.5622,"rr":0.2246},"p":{"ci":394,"fr":0.5646,"rr":0.2228}},"US-AK-SEAPA":{"c":{"ci":24,"fr":0,"rr":1},"p":{"ci":24,"fr":0,"rr":1}},"US-CAL-BANC":{"c":{"ci":448,"fr":0.8569,"rr":0.1431},"e":true,"p":{"ci":448,"fr":0.8569,"rr":0.1431}},"US-CAL-CISO":{"c":{"ci":316,"fr":0.5362,"rr":0.3644},"p":{"ci":332,"fr":0.5363,"rr":0.3643}},"US-CAL-IID":{"c":{"ci":676,"fr":1,"rr":0},"e":true,"p":{"ci":676,"fr":1,"rr":0}},"US-CAL-LDWP":{"c":{"ci":650,"fr":0.9001,"rr":0.0999},"e":true,"p":{"ci":650,"fr":0.9001,"rr":0.0999}},"US-CAL-TIDC":{"c":{"ci":575,"fr":0.9548,"rr":0.0452},"e":true,"p":{"ci":575,"fr":0.9548,"rr":0.0452}},"US-CAR-CPLE":{"c":{"ci":315,"fr":0.4273,"rr":0.0023},"e":true,"p":{"ci":315,"fr":0.4273,"rr":0.0023}},"US-CAR-CPLW":{"c":{"ci":565,"fr":1,"rr":0},"e":true,"p":{"ci":565,"fr":1,"rr":0}},"US-CAR-DUK":{"c":{"ci":267,"fr":0.3774,"rr":0.0329},"e":true,"p":{"ci":266,"fr":0.3774,"rr":0.0329}},"US-CAR-SC":{"c":{"ci":1040,"fr":0.9352,"rr":0.0648},"e":true,"p":{"ci":1040,"fr":0.9352,"rr":0.0648}},"US-CAR-SCEG":{"c":{"ci":396,"fr":0.6103,"rr":0.0527},"e":true,"p":{"ci":396,"fr":0.6103,"rr":0.0527}},"US-CAR-YAD":{"c":{"ci":24,"fr":0,"rr":1},"e":true,"p":{"ci":24,"fr":0,"rr":1}},"US-CENT-SPA":{"c":{"ci":24,"fr":0,"rr":1},"e":true,"p":{"ci":24,"fr":0,"rr":1}},"US-CENT-SWPP":{"c":{"ci":322,"fr":0.3989,"rr":0.5413},"p":{"ci":323,"fr":0.3999,"rr":0.5402}},"US-FLA-FMPP":{"c":{"ci":578,"fr":0.907,"rr":0},"e":true,"p":{"ci":578,"fr":0.907,"rr":0}},"US-FLA-FPC":{"c":{"ci":546,"fr":0.9906,"rr":0.0094},"e":true,"p":{"ci":546,"fr":0.9906,"rr":0.0094}},"US-FLA-FPL":{"c":{"ci":301,"fr":0.6109,"rr":0},"e":true,"p":{"ci":301,"fr":0.6109,"rr":0}},"US-FLA-GVL":{"c":{"ci":613,"fr":1,"rr":0},"e":true,"p":{"ci":613,"fr":1,"rr":0}},"US-FLA-JEA":{"c":{"ci":645,"fr":1,"rr":0},"e":true,"p":{"ci":645,"fr":1,"rr":0}},"US-FLA-SEC":{"c":{"ci":507,"fr":1,"rr":0},"e":true,"p":{"ci":507,"fr":1,"rr":0}},"US-FLA-TAL":{"c":{"ci":484,"fr":1,"rr":0},"e":true,"p":{"ci":484,"fr":1,"rr":0}},"US-FLA-TEC":{"c":{"ci":511,"fr":1,"rr":0},"e":true,"p":{"ci":511,"fr":1,"rr":0}},"US-MIDA-PJM":{"c":{"ci":424,"fr":0.6183,"rr":0.0279},"p":{"ci":425,"fr":0.6213,"rr":0.0269}},"US-MIDW-AECI":{"c":{"ci":582,"fr":0.7855,"rr":0.2112},"e":true,"p":{"ci":597,"fr":0.8082,"rr":0.1918}},"US-MIDW-LGEE":{"c":{"ci":1017,"fr":0.9808,"rr":0.0192},"e":true,"p":{"ci":1017,"fr":0.9808,"rr":0.0192}},"US-MIDW-MISO":{"c":{"ci":451,"fr":0.5697,"rr":0.2689},"e":true,"p":{"ci":455,"fr":0.5715,"rr":0.2769}},"US-NE-ISNE":{"c":{"ci":274,"fr":0.4961,"rr":0.2309},"p":{"ci":283,"fr":0.516,"rr":0.2023}},"US-NW-AVA":{"c":{"ci":245,"fr":0.3986,"rr":0.6014},"e":true,"p":{"ci":245,"fr":0.3986,"rr":0.6014}},"US-NW-BPAT":{"c":{"ci":44,"fr":0.0404,"rr":0.8302},"e":true,"p":{"ci":44,"fr":0.0403,"rr":0.8299}},"US-NW-CHPD":{"c":{"ci":24,"fr":0,"rr":1},"e":true,"p":{"ci":24,"fr":0,"rr":1}},"US-NW-DOPD":{"c":{"ci":24,"fr":0,"rr":1},"e":true,"p":{"ci":24,"fr":0,"rr":1}},"US-NW-GCPD":{"c":{"ci":24,"fr":0,"rr":1},"e":true,"p":{"ci":24,"fr":0,"rr":1}},"US-NW-GRID":{"c":{"ci":519,"fr":0.8587,"rr":0.1413},"e":true,"p":{"ci":519,"fr":0.8587,"rr":0.1413}},"US-NW-IPCO":{"c":{"ci":340,"fr":0.5581,"rr":0.4419},"e":true,"p":{"ci":340,"fr":0.5581,"rr":0.4419}},"US-NW-NEVP":{"c":{"ci":601,"fr":0.972,"rr":0.028},"e":true,"p":{"ci":601,"fr":0.972,"rr":0.028}},"US-NW-NWMT":{"c":{"ci":594,"fr":0.5757,"rr":0.4243},"e":true,"p":{"ci":594,"fr":0.5757,"rr":0.4243}},"US-NW-PACE":{"c":{"ci":607,"fr":0.677,"rr":0.323},"e":true,"p":{"ci":607,"fr":0.677,"rr":0.323}},"US-NW-PACW":{"c":{"ci":598,"fr":0.8328,"rr":0.1672},"e":true,"p":{"ci":598,"fr":0.8328,"rr":0.1672}},"US-NW-PGE":{"c":{"ci":391,"fr":0.6682,"rr":0.3318},"e":true,"p":{"ci":391,"fr":0.6682,"rr":0.3318}},"US-NW-PSCO":{"c":{"ci":431,"fr":0.5167,"rr":0.4816},"e":true,"p":{"ci":434,"fr":0.5201,"rr":0.4799}},"US-NW-PSEI":{"c":{"ci":384,"fr":0.7386,"rr":0.2614},"e":true,"p":{"ci":384,"fr":0.7386,"rr":0.2614}},"US-NW-SCL":{"c":{"ci":24,"fr":0,"rr":1},"e":true,"p":{"ci":24,"fr":0,"rr":1}},"US-NW-TPWR":{"c":{"ci":24,"fr":0,"rr":1},"e":true,"p":{"ci":24,"fr":0,"rr":1}},"US-NW-WACM":{"c":{"ci":648,"fr":0.6092,"rr":0.389},"e":true,"p":{"ci":658,"fr":0.6157,"rr":0.3843}},"US-NW-WAUW":{"c":{"ci":24,"fr":0,"rr":1},"e":true,"p":{"ci":24,"fr":0,"rr":1}},"US-NY-NYIS":{"c":{"ci":305,"fr":0.5321,"rr":0.2125},"p":{"ci":299,"fr":0.542,"rr":0.2389}},"US-SE-SEPA":{"c":{"ci":24,"fr":0,"rr":1},"e":true,"p":{"ci":24,"fr":0,"rr":1}},"US-SE-SOCO":{"c":{"ci":427,"fr":0.688,"rr":0},"e":true,"p":{"ci":427,"fr":0.688,"rr":0}},"US-SW-AZPS":{"c":{"ci":648,"fr":0.9,"rr":0.1},"e":true,"p":{"ci":648,"fr":0.9,"rr":0.1}},"US-SW-EPE":{"c":{"ci":685,"fr":1,"rr":0},"e":true,"p":{"ci":685,"fr":1,"rr":0}},"US-SW-PNM":{"c":{"ci":190,"fr":0.1946,"rr":0.8054},"e":true,"p":{"ci":190,"fr":0.1946,"rr":0.8054}},"US-SW-SRP":{"c":{"ci":295,"fr":0.4746,"rr":0.0035},"e":true,"p":{"ci":295,"fr":0.4746,"rr":0.0035}},"US-SW-TEPC":{"c":{"ci":697,"fr":0.8477,"rr":0.1523},"e":true,"p":{"ci":697,"fr":0.8477,"rr":0.1523}},"US-SW-WALC":{"c":{"ci":318,"fr":0.5871,"rr":0.4129},"e":true,"p":{"ci":318,"fr":0.5871,"rr":0.4129}},"US-TEN-TVA":{"c":{"ci":346,"fr":0.4414,"rr":0.084},"e":true,"p":{"ci":346,"fr":0.4414,"rr":0.084}},"US-TEX-ERCO":{"c":{"ci":340,"fr":0.521,"rr":0.3779},"p":{"ci":340,"fr":0.5211,"rr":0.3778}},"UY":{"c":{"ci":37,"fr":0,"rr":1},"p":{"ci":37,"fr":0,"rr":1}},"XK":{"c":{"ci":598,"fr":0.7384,"rr":0.2102},"e":true,"p":{"ci":820,"fr":1,"rr":0}},"ZA":{"c":{"ci":741,"fr":0.8556,"rr":0.1066},"e":true,"p":{"ci":743,"fr":0.8556,"rr":0.1066}}}}},"stateAggregation":"last_hour"}}